tg_botting/__init__.py
tg_botting/_types.py
tg_botting/abstract.py
tg_botting/bot.py
tg_botting/client.py
tg_botting/cog.py
tg_botting/commands.py
tg_botting/context.py
tg_botting/context_managers.py
tg_botting/conversions.py
tg_botting/cooldowns.py
tg_botting/exceptions.py
tg_botting/general.py
tg_botting/group.py
tg_botting/limiters.py
tg_botting/message.py
tg_botting/objects.py
tg_botting/permissions.py
tg_botting/user.py
tg_botting/utils.py
tg_botting/view.py
tg_botting-2.2.3.dist-info/METADATA
tg_botting-2.2.3.dist-info/WHEEL
tg_botting-2.2.3.dist-info/top_level.txt
tg_botting-2.2.3.dist-info/RECORD
